README.txt
setup.py
PySimLib/Config.py
PySimLib/Log.py
PySimLib/Model.py
PySimLib/Platform.py
PySimLib/Plot.py
PySimLib/Simulation.py
PySimLib/SimulationResult.py
PySimLib/Solver.py
PySimLib/Tool.py
PySimLib/VariableDescriptor.py
PySimLib/__init__.py
PySimLib.egg-info/PKG-INFO
PySimLib.egg-info/SOURCES.txt
PySimLib.egg-info/dependency_links.txt
PySimLib.egg-info/requires.txt
PySimLib.egg-info/top_level.txt
PySimLib/Exceptions/CompilationFailedException.py
PySimLib/Exceptions/SimulationFailedException.py
PySimLib/Exceptions/UncompiledModelException.py
PySimLib/Mat/Mat.py
PySimLib/Mat/Matrix.py
PySimLib/Mat/MatrixTypeEvaluator.py
PySimLib/Mat/OutputStream.py
PySimLib/Mat/TextMatrix.py
PySimLib/Models/ModelicaModel.py
PySimLib/Models/SimulinkModel.py
PySimLib/Solvers/DASSL.py
PySimLib/Solvers/DEABM.py
PySimLib/Solvers/LSODAR.py
PySimLib/Tools/Dymola.py
PySimLib/Tools/ModelicaTool.py
PySimLib/Tools/OpenModelica.py
PySimLib/Tools/Simulink.py