Metadata-Version: 1.0
Name: PySimLib
Version: 1.0.0b7
Summary: The Python Simulation Library allows to simulate Modelica and Simulink models in a platform-independent way.
Home-page: https://gitlab.tubit.tu-berlin.de/a.mehlhase/PySimulationLibrary
Author: Alexandra Mehlhase
Author-email: a.mehlhase@tu-berlin.de
License: GPL
Platform: UNKNOWN
